.gitignore
.gitlab-ci.yml
LICENSE
MANIFEST.in
README.rst
TODO.rst
VERSION
makefile
pyproject.toml
setup.py
demos/2018-03-22-ekekstar-minervino.rst
demos/Diophantine Approximation and MCF algorithms.ipynb
demos/arXiv_1802_03265.rst
demos/arXiv_1808_07768_part1.rst
demos/arXiv_1808_07768_part2.rst
demos/arXiv_1906_01104.rst
demos/arXiv_2012_03892.rst
demos/arXiv_2012_03892v3_doctest.sage
demos/arXiv_2312_03652_doctest.sage
demos/arXiv_2403_03197_doctest.sage
demos/hdr_doctest.sage
docs/Makefile
docs/source/EkEkstar.rst
docs/source/analyze_sage_build.rst
docs/source/aperiodic_monotile.rst
docs/source/arXiv_1808_07768.rst
docs/source/arXiv_1903_06137.rst
docs/source/arXiv_1906_01104.rst
docs/source/beta_numeration_system.rst
docs/source/billiard.rst
docs/source/billiard_nD.rst
docs/source/bispecial_extension_type.rst
docs/source/bond_percolation.rst
docs/source/christoffel_graph.rst
docs/source/coding_of_PETs.rst
docs/source/combinat.rst
docs/source/conf.py
docs/source/cut_and_project_scheme.rst
docs/source/ddim_sturmian_configuration.rst
docs/source/diophantine_approx.rst
docs/source/discrete_plane.rst
docs/source/discrete_subset.rst
docs/source/double_square_tile.rst
docs/source/dyck_3d.rst
docs/source/finite_word.rst
docs/source/fruit.rst
docs/source/graph.rst
docs/source/graph_directed_IFS.rst
docs/source/index.rst
docs/source/infinite_word.rst
docs/source/joyal_bijection.rst
docs/source/kolakoski_word.rst
docs/source/language.rst
docs/source/lyapunov.rst
docs/source/magic_hexagon.rst
docs/source/markov_transformation.rst
docs/source/matrices.rst
docs/source/matrix_cocycle.rst
docs/source/mult_cont_frac.rst
docs/source/ostrowski.rst
docs/source/partial_injection.rst
docs/source/piecewise_affine_transformation.rst
docs/source/polyhedron_exchange_transformation.rst
docs/source/polyhedron_partition.rst
docs/source/q_markoff.rst
docs/source/random_team_creation.rst
docs/source/ranking_scale.rst
docs/source/sturmian_subshift.rst
docs/source/substitution_2d.rst
slabbe.egg-info/PKG-INFO
slabbe.egg-info/SOURCES.txt
slabbe.egg-info/dependency_links.txt
slabbe.egg-info/requires.txt
slabbe.egg-info/top_level.txt