Metadata-Version: 2.1
Name: slabbe
Version: 0.8.0
Summary: Sebastien Labbe's Research code
Author-email: Sebastien Labbe <slabbe@ulg.ac.be>
License: GPLv2+
Project-URL: Homepage, http://gitlab.com/seblabbe/slabbe
Keywords: sagemath,combinatorics,discrete geometry,symbolic dynamics
Classifier: Development Status :: 4 - Beta
Classifier: Intended Audience :: Science/Research
Classifier: License :: OSI Approved :: GNU General Public License v2 or later (GPLv2+)
Classifier: Programming Language :: Python :: 3.7
Classifier: Topic :: Scientific/Engineering :: Mathematics
License-File: LICENSE
Requires-Dist: cysignals
Provides-Extra: timeparse
Requires-Dist: pytimeparse; extra == "timeparse"
Provides-Extra: roman
Requires-Dist: roman; extra == "roman"
